{
  "word": "Clearness",
  "pronunciation": "CLEARNESS,",
  "definitions": [
    {
      "type": "noun",
      "text": "1. Freedom from foul or extraneous matter; purity; as the clearness of water, or other liquor.\n2. Freedom from obstruction or incumbrance; as the clearness of the ground.\n3. Freedom from fogs or clouds; openness; as the clearness of the sky. It generally expresses less than brightness or splendor. Exodus 24:10.\n4. Distinctness; perspicuity; luminousness; as the clearness of reason, of views, of arguments, of explanations.\n5. Plainness, or plain dealing; sincerity; honesty; fairness; candor.\n6. Freedom from imputation of ill.\n7. Freedom from spots, or any thing that disfigures; as the clearness of the skin."
    }
  ]
}